validb/__init__.py
validb/__main__.py
validb/_classloader.py
validb/_detected.py
validb/_detectiondata.py
validb/_embedded_vars.py
validb/_embedder.py
validb/_validate.py
validb/config/__init__.py
validb/config/_config.py
validb/config/_load.py
validb/config/_type.py
validb/csvmapping/__init__.py
validb/csvmapping/_csvmapping.py
validb/datasources/__init__.py
validb/datasources/_datasource.py
validb/datasources/sqlalchemy/__init__.py
validb/datasources/sqlalchemy/_datasource.py
validb/formatter/__init__.py
validb/formatter/_formatter.py
validb/rules/__init__.py
validb/rules/_rule.py
validb/rules/sqlalchemy/__init__.py
validb/rules/sqlalchemy/_rule.py
validb-0.0.6.dist-info/METADATA
validb-0.0.6.dist-info/WHEEL
validb-0.0.6.dist-info/top_level.txt
validb-0.0.6.dist-info/RECORD
