Metadata-Version: 2.1
Name: validb
Version: 0.0.6
Summary: validate DB data
Author-email: k-izumi <k.izumi.ysk@gmail.com>
License: MIT License
Project-URL: Homepage, https://github.com/unaguna/validb
Project-URL: Repository, https://github.com/unaguna/validb.git
Classifier: Development Status :: 3 - Alpha
Classifier: Programming Language :: Python :: 3
Classifier: Programming Language :: Python :: 3.8
Requires-Python: >=3.8
Requires-Dist: click
